odoo/addons/website_sale_product_attribute_filter_order/README.rst
odoo/addons/website_sale_product_attribute_filter_order/__init__.py
odoo/addons/website_sale_product_attribute_filter_order/__manifest__.py
odoo/addons/website_sale_product_attribute_filter_order/i18n/ca.po
odoo/addons/website_sale_product_attribute_filter_order/i18n/es.po
odoo/addons/website_sale_product_attribute_filter_order/i18n/it.po
odoo/addons/website_sale_product_attribute_filter_order/i18n/website_sale_product_attribute_filter_order.pot
odoo/addons/website_sale_product_attribute_filter_order/readme/CONFIGURE.md
odoo/addons/website_sale_product_attribute_filter_order/readme/CONTRIBUTORS.md
odoo/addons/website_sale_product_attribute_filter_order/readme/DESCRIPTION.md
odoo/addons/website_sale_product_attribute_filter_order/readme/ROADMAP.md
odoo/addons/website_sale_product_attribute_filter_order/readme/USAGE.md
odoo/addons/website_sale_product_attribute_filter_order/static/description/attributes00.png
odoo/addons/website_sale_product_attribute_filter_order/static/description/icon.png
odoo/addons/website_sale_product_attribute_filter_order/static/description/index.html
odoo/addons/website_sale_product_attribute_filter_order/templates/website_sale.xml
odoo/addons/website_sale_product_attribute_filter_order/views/snippets/snippets.xml
odoo_addon_website_sale_product_attribute_filter_order-17.0.1.0.0.4.dist-info/METADATA
odoo_addon_website_sale_product_attribute_filter_order-17.0.1.0.0.4.dist-info/WHEEL
odoo_addon_website_sale_product_attribute_filter_order-17.0.1.0.0.4.dist-info/top_level.txt
odoo_addon_website_sale_product_attribute_filter_order-17.0.1.0.0.4.dist-info/RECORD
