Metadata-Version: 2.1
Name: odoo-addon-website_sale_product_attribute_filter_order
Version: 17.0.1.0.0.4
Requires-Python: >=3.10
Requires-Dist: odoo>=17.0a,<17.1dev
Summary: Move active checkbox options to the first place of the list
Home-page: https://github.com/OCA/e-commerce
License: LGPL-3
Author: Tecnativa, Odoo Community Association (OCA)
Author-email: support@odoo-community.org
Classifier: Programming Language :: Python
Classifier: Framework :: Odoo
Classifier: Framework :: Odoo :: 17.0
Classifier: License :: OSI Approved :: GNU Lesser General Public License v3 (LGPLv3)
